flask_restframework/__init__.py
flask_restframework/authentication.py
flask_restframework/base_test.py
flask_restframework/exceptions.py
flask_restframework/middlewares.py
flask_restframework/paginations.py
flask_restframework/permissions.py
flask_restframework/status.py
flask_restframework/test.py
flask_restframework/test_init.py
flask_restframework/test_views.py
flask_restframework/user.py
flask_restframework/views.py
flask_rest_framework-0.0.2.dist-info/METADATA
flask_rest_framework-0.0.2.dist-info/WHEEL
flask_rest_framework-0.0.2.dist-info/top_level.txt
flask_rest_framework-0.0.2.dist-info/RECORD
