Metadata-Version: 2.1
Name: flask-rest-framework
Version: 0.0.2
Summary: UNKNOWN
Home-page: https://github.com/waro163/flask-restframework
Author: waro163
Author-email: waro163@163.com
License: MIT
Platform: UNKNOWN
Classifier: Environment :: Web Environment
Classifier: Framework :: Flask
Classifier: Operating System :: OS Independent
Classifier: Programming Language :: Python
Classifier: License :: OSI Approved :: MIT License
Classifier: Topic :: Internet :: WWW/HTTP
Requires-Python: >=3.5
Requires-Dist: flask (>=2.0.0)
